aug_tool/__init__.py
aug_tool/factory.py
aug_tool/dataAugmentor/__init__.py
aug_tool/dataAugmentor/annAug.py
aug_tool/dataAugmentor/dataAug.py
aug_tool/dataAugmentor/imgAug.py
aug_tool/dataAugmentor/txtAug.py
aug_tool/dataAugmentor/xmlAug.py
aug_tool/dataOpener/__init__.py
aug_tool/dataOpener/annOp.py
aug_tool/dataOpener/dataOp.py
aug_tool/dataOpener/imgOp.py
aug_tool/dataOpener/txtOp.py
aug_tool/dataOpener/xmlOp.py
aug_tool/dataSaver/__init__.py
aug_tool/dataSaver/annSav.py
aug_tool/dataSaver/dataSav.py
aug_tool/dataSaver/imgSav.py
aug_tool/dataSaver/txtSav.py
aug_tool/dataSaver/xmlSav.py
aug_tool-0.2.dist-info/LICENCE
aug_tool-0.2.dist-info/METADATA
aug_tool-0.2.dist-info/WHEEL
aug_tool-0.2.dist-info/top_level.txt
aug_tool-0.2.dist-info/RECORD
